mudae/main.py
mudae-0.1.2.dist-info/METADATA
mudae-0.1.2.dist-info/WHEEL
mudae-0.1.2.dist-info/entry_points.txt
mudae-0.1.2.dist-info/top_level.txt
mudae-0.1.2.dist-info/RECORD
