Metadata-Version: 2.4
Name: mudae
Version: 0.1.2
Summary: Better Playwright MCP
Requires-Python: >=3.10
Requires-Dist: mcp[cli]>=1.9.2
Requires-Dist: playwright>=1.52.0
